{
    "variants": {
        "facing=north,active=false": { "model": "advanced_reborn:block/enchantment_extractor" },
        "facing=south,active=false": { "model": "advanced_reborn:block/enchantment_extractor", "y": 180 },
        "facing=west,active=false":  { "model": "advanced_reborn:block/enchantment_extractor", "y": 270 },
        "facing=east,active=false":  { "model": "advanced_reborn:block/enchantment_extractor", "y": 90 },
        "facing=north,active=true": { "model": "advanced_reborn:block/enchantment_extractor_on" },
        "facing=south,active=true": { "model": "advanced_reborn:block/enchantment_extractor_on", "y": 180 },
        "facing=west,active=true":  { "model": "advanced_reborn:block/enchantment_extractor_on", "y": 270 },
        "facing=east,active=true":  { "model": "advanced_reborn:block/enchantment_extractor_on", "y": 90 }
    }
}
